rough_graph_mapper/__init__.py
rough_graph_mapper/command_line_interface.py
rough_graph_mapper/filter_graphalignments.py
rough_graph_mapper/linear_to_graph_mapper.py
rough_graph_mapper/sam_to_graph_aligner.py
rough_graph_mapper/single_read_aligner.py
rough_graph_mapper/traverser.py
rough_graph_mapper/util.py
rough_graph_mapper-0.0.4.dist-info/METADATA
rough_graph_mapper-0.0.4.dist-info/WHEEL
rough_graph_mapper-0.0.4.dist-info/entry_points.txt
rough_graph_mapper-0.0.4.dist-info/top_level.txt
rough_graph_mapper-0.0.4.dist-info/RECORD
